main.py
settings.py
db/__init__.py
db/database.py
db/schema_versions.py
db/semantic_search.py
db/sources.py
db/test_database.py
db/test_precomputed_data_workflow.py
db/test_schema_versions.py
db/test_sources.py
mcp_mcp-0.2.0.dist-info/licenses/LICENSE
mcp_mcp-0.2.0.dist-info/METADATA
mcp_mcp-0.2.0.dist-info/WHEEL
mcp_mcp-0.2.0.dist-info/entry_points.txt
mcp_mcp-0.2.0.dist-info/top_level.txt
mcp_mcp-0.2.0.dist-info/RECORD
