Metadata-Version: 2.4
Name: mcp-mcp
Version: 0.2.0
Summary: MCP-MCP: Meta-MCP Server for dynamic MCP server discovery and provisioning
Author: Wojciech Wojtyniak
License-Expression: MIT
Project-URL: Homepage, https://github.com/wojtyniak/mcp-mcp
Project-URL: Repository, https://github.com/wojtyniak/mcp-mcp
Project-URL: Documentation, https://github.com/wojtyniak/mcp-mcp#readme
Project-URL: Issues, https://github.com/wojtyniak/mcp-mcp/issues
Keywords: mcp,model-context-protocol,ai,claude,server-discovery
Classifier: Development Status :: 3 - Alpha
Classifier: Intended Audience :: Developers
Classifier: Operating System :: OS Independent
Classifier: Programming Language :: Python :: 3
Classifier: Programming Language :: Python :: 3.13
Classifier: Topic :: Software Development :: Libraries :: Python Modules
Classifier: Topic :: Scientific/Engineering :: Artificial Intelligence
Classifier: Environment :: Console
Requires-Python: >=3.13
License-File: LICENSE
Requires-Dist: httpx>=0.27.0
Requires-Dist: mcp>=1.9.4
Requires-Dist: pydantic-settings>=2.10.1
Requires-Dist: rich>=14.0.0
Requires-Dist: sentence-transformers>=4.1.0
Dynamic: license-file
